{
  "plugins": {
    "bamboo.nvim": {
      "rev": "1309bc88bffcf1bedc3e84e7fa9004de93da774a",
      "src": "https://github.com/ribru17/bamboo.nvim"
    },
    "blink.cmp": {
      "rev": "4b18c32adef2898f95cdef6192cbd5796c1a332d",
      "src": "https://github.com/Saghen/blink.cmp",
      "version": "1.0.0 - 2.0.0"
    },
    "everforest-nvim": {
      "rev": "557bce922401e247a596583679bc181d4d688554",
      "src": "https://github.com/neanias/everforest-nvim"
    },
    "flexoki-neovim": {
      "rev": "c3e2251e813d29d885a7cbbe9808a7af234d845d",
      "src": "https://github.com/kepano/flexoki-neovim"
    },
    "fzf-lua": {
      "rev": "d9508cc1d05ffcdc91a32dfd38fc1013a56b20da",
      "src": "https://github.com/ibhagwan/fzf-lua"
    },
    "gitsigns.nvim": {
      "rev": "7c4faa3540d0781a28588cafbd4dd187a28ac6e3",
      "src": "https://github.com/lewis6991/gitsigns.nvim"
    },
    "grug-far.nvim": {
      "rev": "ac52ee2d87399dfd7b0d59d5b1d2bbaf2a4028f1",
      "src": "https://github.com/MagicDuck/grug-far.nvim"
    },
    "gruvbox.nvim": {
      "rev": "561126520034a1dac2f78ab063db025d12555998",
      "src": "https://github.com/ellisonleao/gruvbox.nvim"
    },
    "harpoon": {
      "rev": "87b1a3506211538f460786c23f98ec63ad9af4e5",
      "src": "https://github.com/ThePrimeagen/harpoon",
      "version": "'harpoon2'"
    },
    "kanagawa.nvim": {
      "rev": "aef7f5cec0a40dbe7f3304214850c472e2264b10",
      "src": "https://github.com/rebelot/kanagawa.nvim"
    },
    "lualine.nvim": {
      "rev": "47f91c416daef12db467145e16bed5bbfe00add8",
      "src": "https://github.com/nvim-lualine/lualine.nvim"
    },
    "markview.nvim": {
      "rev": "239feb70ed1cfc26e2c91b32590fd63f7b015599",
      "src": "https://github.com/OXY2DEV/markview.nvim"
    },
    "mason-lspconfig.nvim": {
      "rev": "a324581a3c83fdacdb9804b79de1cbe00ce18550",
      "src": "https://github.com/mason-org/mason-lspconfig.nvim"
    },
    "mason-tool-installer.nvim": {
      "rev": "443f1ef8b5e6bf47045cb2217b6f748a223cf7dc",
      "src": "https://github.com/WhoIsSethDaniel/mason-tool-installer.nvim"
    },
    "mason.nvim": {
      "rev": "44d1e90e1f66e077268191e3ee9d2ac97cc18e65",
      "src": "https://github.com/mason-org/mason.nvim"
    },
    "matteblack.nvim": {
      "rev": "a8a039f5d6189b28d76fa0221e64965efec7e996",
      "src": "https://github.com/tahayvr/matteblack.nvim"
    },
    "mini.cursorword": {
      "rev": "8dcf45bc820f3c5f778960ba55206938246b70b7",
      "src": "https://github.com/nvim-mini/mini.cursorword"
    },
    "mini.icons": {
      "rev": "5b9076dae1bfbe47ba4a14bc8b967cde0ab5d77e",
      "src": "https://github.com/nvim-mini/mini.icons"
    },
    "mini.pick": {
      "rev": "8521fe21df86e08d9e4b3c3f3a7d50e47954e1af",
      "src": "https://github.com/nvim-mini/mini.pick"
    },
    "mini.surround": {
      "rev": "d205d1741d1fcc1f3117b4e839bf00f74ad72fa2",
      "src": "https://github.com/nvim-mini/mini.surround"
    },
    "minimal.nvim": {
      "rev": "22d837b",
      "src": "https://github.com/Yazeed1s/minimal.nvim"
    },
    "monokai-pro.nvim": {
      "rev": "5b06ae0736813b1c65d76a4be9edbe92be0b9c74",
      "src": "https://github.com/gthelding/monokai-pro.nvim"
    },
    "neovim": {
      "rev": "cf2a288696b03d0934da713d66c6d71557b5c997",
      "src": "https://github.com/rose-pine/neovim"
    },
    "nightfox.nvim": {
      "rev": "ba47d4b4c5ec308718641ba7402c143836f35aa9",
      "src": "https://github.com/EdenEast/nightfox.nvim"
    },
    "nui.nvim": {
      "rev": "de740991c12411b663994b2860f1a4fd0937c130",
      "src": "https://github.com/MunifTanjim/nui.nvim"
    },
    "nvim": {
      "rev": "12c004cde3f36cb1d57242f1e6aac46b09a0e5b4",
      "src": "https://github.com/catppuccin/nvim"
    },
    "nvim-lspconfig": {
      "rev": "2163c54bb6cfec53e3e555665ada945b8c8331b9",
      "src": "https://github.com/neovim/nvim-lspconfig"
    },
    "nvim-notify": {
      "rev": "8701bece920b38ea289b457f902e2ad184131a5d",
      "src": "https://github.com/rcarriga/nvim-notify"
    },
    "nvim-spectre": {
      "rev": "72f56f7",
      "src": "https://github.com/nvim-pack/nvim-spectre"
    },
    "nvim-treesitter": {
      "rev": "42fc28ba918343ebfd5565147a42a26580579482",
      "src": "https://github.com/nvim-treesitter/nvim-treesitter"
    },
    "plenary.nvim": {
      "rev": "b9fd5226c2f76c951fc8ed5923d85e4de065e509",
      "src": "https://github.com/nvim-lua/plenary.nvim"
    },
    "render-markdown.nvim": {
      "rev": "fcea0776a3019f49360b7aaec3318630633c522d",
      "src": "https://github.com/MeanderingProgrammer/render-markdown.nvim"
    },
    "rustaceanvim": {
      "rev": "f2f0c1231a5b019dbc1fd6dafac1751c878925a3",
      "src": "https://github.com/mrcjkb/rustaceanvim"
    },
    "tabby.nvim": {
      "rev": "3c130e1fcb598ce39a9c292847e32d7c3987cf11",
      "src": "https://github.com/nanozuki/tabby.nvim"
    },
    "tokyonight.nvim": {
      "rev": "5da1b76e64daf4c5d410f06bcb6b9cb640da7dfd",
      "src": "https://github.com/folke/tokyonight.nvim"
    },
    "vague.nvim": {
      "rev": "8c4643f8a5106dbc492918f86ff6b5c81111ce9a",
      "src": "https://github.com/vague2k/vague.nvim"
    },
    "vscode-diff.nvim": {
      "rev": "96845f95bc5539c8e2a0ab88223c5033f302fcd9",
      "src": "https://github.com/esmuellert/vscode-diff.nvim",
      "version": "'next'"
    },
    "which-key.nvim": {
      "rev": "3aab2147e74890957785941f0c1ad87d0a44c15a",
      "src": "https://github.com/folke/which-key.nvim"
    },
    "yazi.nvim": {
      "rev": "54097e2cb5282d8c92c6dd16c9868ed3b3273a24",
      "src": "https://github.com/mikavilpas/yazi.nvim"
    }
  }
}